{
    "/js/app.js": "/js/app.js",
    "/css/app.css": "/css/app.css",
    "/0.9c82caad4c449d694312.hot-update.js": "/0.9c82caad4c449d694312.hot-update.js",
    "/0.4ce3bac197d4e3c2e3d6.hot-update.js": "/0.4ce3bac197d4e3c2e3d6.hot-update.js",
    "/0.5b0807c6710a6eb7d4e4.hot-update.js": "/0.5b0807c6710a6eb7d4e4.hot-update.js",
    "/0.d4d52f7d5c8c90b9b4fb.hot-update.js": "/0.d4d52f7d5c8c90b9b4fb.hot-update.js",
    "/0.11d42f7353a7c58ec95c.hot-update.js": "/0.11d42f7353a7c58ec95c.hot-update.js",
    "/0.4a1c132428b7d5003fb4.hot-update.js": "/0.4a1c132428b7d5003fb4.hot-update.js",
    "/0.9961c80aebebe7cb5d11.hot-update.js": "/0.9961c80aebebe7cb5d11.hot-update.js",
    "/0.f32fe1e0f708a5814f3d.hot-update.js": "/0.f32fe1e0f708a5814f3d.hot-update.js",
    "/0.04b6124c4885bd4cbc78.hot-update.js": "/0.04b6124c4885bd4cbc78.hot-update.js",
    "/0.aedd9772395d00f54822.hot-update.js": "/0.aedd9772395d00f54822.hot-update.js",
    "/0.750bb446559d6a7b2de4.hot-update.js": "/0.750bb446559d6a7b2de4.hot-update.js",
    "/0.352f03cfb33bee0febda.hot-update.js": "/0.352f03cfb33bee0febda.hot-update.js",
    "/0.1e839f03f3dc172418b5.hot-update.js": "/0.1e839f03f3dc172418b5.hot-update.js",
    "/0.189703a267bcbbd2c33c.hot-update.js": "/0.189703a267bcbbd2c33c.hot-update.js",
    "/0.0134c59200e12b80812c.hot-update.js": "/0.0134c59200e12b80812c.hot-update.js",
    "/0.5b983c4677f977859af4.hot-update.js": "/0.5b983c4677f977859af4.hot-update.js",
    "/0.9dc734799c6231153856.hot-update.js": "/0.9dc734799c6231153856.hot-update.js",
    "/0.b2bad8cae9e4e600aebe.hot-update.js": "/0.b2bad8cae9e4e600aebe.hot-update.js",
    "/0.2aa85a97bf48e1065ce7.hot-update.js": "/0.2aa85a97bf48e1065ce7.hot-update.js",
    "/0.29cecba508efbd3f26a7.hot-update.js": "/0.29cecba508efbd3f26a7.hot-update.js"
}
