{
    "/js/app.js": "/js/app.js",
    "/css/app.css": "/css/app.css",
    "/0.a0d1b8ccf02c574ec4b6.hot-update.js": "/0.a0d1b8ccf02c574ec4b6.hot-update.js",
    "/0.4396e7e42093a3fe9e20.hot-update.js": "/0.4396e7e42093a3fe9e20.hot-update.js",
    "/0.4fc9cff8524007c93630.hot-update.js": "/0.4fc9cff8524007c93630.hot-update.js",
    "/0.07c91b508c6ab7da28b0.hot-update.js": "/0.07c91b508c6ab7da28b0.hot-update.js",
    "/0.90c369a8cd8a1bea67db.hot-update.js": "/0.90c369a8cd8a1bea67db.hot-update.js",
    "/0.9eceaeef18cbb8b5101a.hot-update.js": "/0.9eceaeef18cbb8b5101a.hot-update.js",
    "/0.0a0c4220f53d528e6853.hot-update.js": "/0.0a0c4220f53d528e6853.hot-update.js",
    "/0.4388102940ac60ae1254.hot-update.js": "/0.4388102940ac60ae1254.hot-update.js",
    "/0.2ef19ae6a9c6c46971ca.hot-update.js": "/0.2ef19ae6a9c6c46971ca.hot-update.js",
    "/0.09756554b9470cbed447.hot-update.js": "/0.09756554b9470cbed447.hot-update.js",
    "/0.4e098f1859f3b4108b56.hot-update.js": "/0.4e098f1859f3b4108b56.hot-update.js",
    "/0.c33d285d571deccf42f8.hot-update.js": "/0.c33d285d571deccf42f8.hot-update.js",
    "/0.4e5e6e868d011491b68f.hot-update.js": "/0.4e5e6e868d011491b68f.hot-update.js",
    "/0.2fcbfe80fd696eda4cdf.hot-update.js": "/0.2fcbfe80fd696eda4cdf.hot-update.js",
    "/0.52631777e8aa68d0106d.hot-update.js": "/0.52631777e8aa68d0106d.hot-update.js",
    "/0.57c84b852b6ca5274849.hot-update.js": "/0.57c84b852b6ca5274849.hot-update.js",
    "/0.42fe3264cf336371a1b6.hot-update.js": "/0.42fe3264cf336371a1b6.hot-update.js",
    "/0.de2044382f2d4e95cdf8.hot-update.js": "/0.de2044382f2d4e95cdf8.hot-update.js",
    "/0.681388b92287ed69f30d.hot-update.js": "/0.681388b92287ed69f30d.hot-update.js",
    "/0.ee8c98671684aeeeb24a.hot-update.js": "/0.ee8c98671684aeeeb24a.hot-update.js",
    "/0.bf352de81e36c469a8b8.hot-update.js": "/0.bf352de81e36c469a8b8.hot-update.js",
    "/0.eabe69fb1d646b0cabf1.hot-update.js": "/0.eabe69fb1d646b0cabf1.hot-update.js",
    "/0.7b0d189081528b0d06e6.hot-update.js": "/0.7b0d189081528b0d06e6.hot-update.js",
    "/0.53382d14cd3f6e7af5c5.hot-update.js": "/0.53382d14cd3f6e7af5c5.hot-update.js",
    "/0.e53e1b81285526719df0.hot-update.js": "/0.e53e1b81285526719df0.hot-update.js",
    "/0.0c67268cfbfe0653ddea.hot-update.js": "/0.0c67268cfbfe0653ddea.hot-update.js",
    "/0.7b2a694733cb31efb957.hot-update.js": "/0.7b2a694733cb31efb957.hot-update.js",
    "/0.63f65060b31a04fddbc5.hot-update.js": "/0.63f65060b31a04fddbc5.hot-update.js",
    "/0.d13904d14f66c00ed931.hot-update.js": "/0.d13904d14f66c00ed931.hot-update.js",
    "/0.a0062e914e30206504a9.hot-update.js": "/0.a0062e914e30206504a9.hot-update.js",
    "/0.9e9d2ddba5bf31eb0eb0.hot-update.js": "/0.9e9d2ddba5bf31eb0eb0.hot-update.js",
    "/0.13651f1480c774829d42.hot-update.js": "/0.13651f1480c774829d42.hot-update.js",
    "/0.af421b885b8a08b3856e.hot-update.js": "/0.af421b885b8a08b3856e.hot-update.js",
    "/0.b87e3ac108952611adff.hot-update.js": "/0.b87e3ac108952611adff.hot-update.js",
    "/0.37f75121dc360cced80a.hot-update.js": "/0.37f75121dc360cced80a.hot-update.js",
    "/0.4477b38cb3c6438dfe5d.hot-update.js": "/0.4477b38cb3c6438dfe5d.hot-update.js",
    "/0.1b498348339c322000b8.hot-update.js": "/0.1b498348339c322000b8.hot-update.js",
    "/0.f5eaa399de3029d087b7.hot-update.js": "/0.f5eaa399de3029d087b7.hot-update.js",
    "/0.2944bb2d1d8651715243.hot-update.js": "/0.2944bb2d1d8651715243.hot-update.js",
    "/0.d9632353305a38ffcca9.hot-update.js": "/0.d9632353305a38ffcca9.hot-update.js",
    "/0.c05658d60f3d1b099fcf.hot-update.js": "/0.c05658d60f3d1b099fcf.hot-update.js",
    "/0.90c896f017f097fe964c.hot-update.js": "/0.90c896f017f097fe964c.hot-update.js",
    "/0.642a21b1aa38522d49c9.hot-update.js": "/0.642a21b1aa38522d49c9.hot-update.js",
    "/0.d2399de5ae2e1f93ad08.hot-update.js": "/0.d2399de5ae2e1f93ad08.hot-update.js",
    "/0.58ef4745dd5215e8b93c.hot-update.js": "/0.58ef4745dd5215e8b93c.hot-update.js",
    "/0.414969f18b02077d57d7.hot-update.js": "/0.414969f18b02077d57d7.hot-update.js",
    "/0.2a56f1860b73102a7ffa.hot-update.js": "/0.2a56f1860b73102a7ffa.hot-update.js",
    "/0.55d7381d46a151b3779c.hot-update.js": "/0.55d7381d46a151b3779c.hot-update.js",
    "/0.014e8fb47b99d71ee18c.hot-update.js": "/0.014e8fb47b99d71ee18c.hot-update.js"
}
